documentgraph/__init__.py
documentgraph/__main__.py
documentgraph/cli.py
documentgraph/config.py
documentgraph/extraction.py
documentgraph/loading.py
documentgraph/main.py
documentgraph/models.py
documentgraph/transformation.py
tests/test_loading.py
tests/test_transformation.py
documentgraph-0.1.2.dist-info/LICENSE
documentgraph-0.1.2.dist-info/METADATA
documentgraph-0.1.2.dist-info/WHEEL
documentgraph-0.1.2.dist-info/entry_points.txt
documentgraph-0.1.2.dist-info/top_level.txt
documentgraph-0.1.2.dist-info/RECORD
