Metadata-Version: 2.1
Name: documentgraph
Version: 0.1.2
Summary: A document analysis pipeline with knowledge graph
Author-email: Luise Higuera <luisehica@gmail.com>
Project-URL: Homepage, https://github.com/complexluise/documentgraph
Project-URL: Issues, https://github.com/complexluise/documentgraph/issues
Classifier: Programming Language :: Python :: 3
Classifier: License :: OSI Approved :: Apache Software License
Classifier: Operating System :: OS Independent
Requires-Python: >=3.10
License-File: LICENSE
Requires-Dist: langchain-core==0.3.6
Requires-Dist: langchain-text-splitters==0.3.0
Requires-Dist: neo4j==5.25.0
Requires-Dist: langchain-experimental==0.3.2
Requires-Dist: langchain-openai==0.2.1
Provides-Extra: dev
Requires-Dist: pytest==8.3.3; extra == "dev"
Requires-Dist: black; extra == "dev"
Requires-Dist: isort; extra == "dev"
Requires-Dist: flake8; extra == "dev"
